Metadata-Version: 1.0
Name: ctc-distributions
Version: 0.1
Summary: Gaussian and Binomial distributions
Home-page: UNKNOWN
Author: Conrado T. Catindig
Author-email: nowelsi@yahoo.com
License: UNKNOWN
Platform: UNKNOWN
